[{"id":1,"name":"sweet almond oil","price":350,"description":"hair and skin oil","quantity":30,"product_type":"oil"},{"id":2,"name":"lavender oil","price":350,"description":"hair and skin oil","quantity":25,"product_type":"oil"},{"id":3,"name":"skin aqua","price":370,"description":"moisturing serum","quantity":12,"product_type":"serum"},{"id":4,"name":"victoria secret","price":1500,"description":"perfume","quantity":250,"product_type":"perfume"},{"id":5,"name":"diva","price":350,"description":"toner and hydrating mist","product_type":"toner","quantity":2}]